enhomie/__init__.py
enhomie/conftest.py
enhomie/py.typed
enhomie/version.txt
enhomie/builtins/__init__.py
enhomie/builtins/models.py
enhomie/builtins/period.py
enhomie/builtins/regexp.py
enhomie/builtins/store.py
enhomie/builtins/params/__init__.py
enhomie/builtins/params/period.py
enhomie/builtins/params/regexp.py
enhomie/builtins/params/store.py
enhomie/builtins/test/__init__.py
enhomie/builtins/test/test_models.py
enhomie/builtins/test/test_period.py
enhomie/builtins/test/test_regexp.py
enhomie/builtins/test/test_store.py
enhomie/execution/__init__.py
enhomie/execution/action.py
enhomie/execution/backup.py
enhomie/execution/config.py
enhomie/execution/crypts.py
enhomie/execution/desired.py
enhomie/execution/dumped.py
enhomie/execution/persist.py
enhomie/execution/restful.py
enhomie/execution/service.py
enhomie/execution/test/__init__.py
enhomie/execution/test/test_action.py
enhomie/execution/test/test_backup.py
enhomie/execution/test/test_config.py
enhomie/execution/test/test_crypts.py
enhomie/execution/test/test_desired.py
enhomie/execution/test/test_dumped.py
enhomie/execution/test/test_persist.py
enhomie/execution/test/test_restful.py
enhomie/execution/test/test_service.py
enhomie/homie/__init__.py
enhomie/homie/common.py
enhomie/homie/config.py
enhomie/homie/homie.py
enhomie/homie/models.py
enhomie/homie/service.py
enhomie/homie/addons/__init__.py
enhomie/homie/addons/aspired.py
enhomie/homie/addons/desired.py
enhomie/homie/addons/jinja2.py
enhomie/homie/addons/logger.py
enhomie/homie/addons/persist.py
enhomie/homie/addons/queue.py
enhomie/homie/addons/test/__init__.py
enhomie/homie/addons/test/test_aspired.py
enhomie/homie/addons/test/test_desired.py
enhomie/homie/addons/test/test_logger.py
enhomie/homie/addons/test/test_persist.py
enhomie/homie/addons/test/test_queue.py
enhomie/homie/childs/__init__.py
enhomie/homie/childs/aspire.py
enhomie/homie/childs/child.py
enhomie/homie/childs/desire.py
enhomie/homie/childs/device.py
enhomie/homie/childs/group.py
enhomie-0.13.11.dist-info/licenses/LICENSE
enhomie-0.13.11.dist-info/METADATA
enhomie-0.13.11.dist-info/WHEEL
enhomie-0.13.11.dist-info/top_level.txt
enhomie-0.13.11.dist-info/RECORD
