Metadata-Version: 2.4
Name: enhomie
Version: 0.13.11
Summary: Enasis Network Homie Automate
License: MIT
Project-URL: Source, https://github.com/enasisnetwork/enhomie
Project-URL: Documentation, https://enasisnetwork.github.io/enhomie/sphinx
Classifier: Programming Language :: Python :: 3
Classifier: Programming Language :: Python :: 3.11
Classifier: Programming Language :: Python :: 3.12
Requires-Python: >=3.11
License-File: LICENSE
Requires-Dist: encommon>=0.22.11
Requires-Dist: enconnect>=0.17.18
Requires-Dist: fastapi
Requires-Dist: urllib3
Requires-Dist: uvicorn
Dynamic: license-file
